clipper_admin/VERSION.txt
clipper_admin/__init__.py
clipper_admin/clipper_admin.py
clipper_admin/container_manager.py
clipper_admin/decorators.py
clipper_admin/exceptions.py
clipper_admin/version.py
clipper_admin/deployers/__init__.py
clipper_admin/deployers/deployer_utils.py
clipper_admin/deployers/keras.py
clipper_admin/deployers/mxnet.py
clipper_admin/deployers/onnx.py
clipper_admin/deployers/pyspark.py
clipper_admin/deployers/python.py
clipper_admin/deployers/pytorch.py
clipper_admin/deployers/tensorflow.py
clipper_admin/docker/__init__.py
clipper_admin/docker/docker_container_manager.py
clipper_admin/docker/docker_metric_utils.py
clipper_admin/docker/logging/__init__.py
clipper_admin/docker/logging/clipper_fluentd.conf
clipper_admin/docker/logging/docker_logging_utils.py
clipper_admin/docker/logging/fluentd.py
clipper_admin/kubernetes/__init__.py
clipper_admin/kubernetes/kubernetes_container_manager.py
clipper_admin/kubernetes/kubernetes_metric_utils.py
clipper_admin/kubernetes/mgmt-frontend-deployment.yaml
clipper_admin/kubernetes/mgmt-frontend-service.yaml
clipper_admin/kubernetes/model-container-template.yaml
clipper_admin/kubernetes/prom_configmap.yaml
clipper_admin/kubernetes/prom_deployment.yaml
clipper_admin/kubernetes/prom_service.yaml
clipper_admin/kubernetes/query-frontend-deployment.yaml
clipper_admin/kubernetes/query-frontend-rpc-service.yaml
clipper_admin/kubernetes/query-frontend-service.yaml
clipper_admin/kubernetes/rbac_cluster_role.yaml
clipper_admin/kubernetes/rbac_cluster_role_binding.yaml
clipper_admin/kubernetes/redis-deployment.yaml
clipper_admin/kubernetes/redis-service.yaml
clipper_admin/metrics/__init__.py
clipper_admin/metrics/client.py
clipper_admin/metrics/config.py
clipper_admin/metrics/schema.py
clipper_admin/metrics/server.py
clipper_admin-0.4.1.dist-info/LICENSE.txt
clipper_admin-0.4.1.dist-info/METADATA
clipper_admin-0.4.1.dist-info/RECORD
clipper_admin-0.4.1.dist-info/WHEEL
clipper_admin-0.4.1.dist-info/top_level.txt
